py3tftpsql
