Metadata-Version: 2.1
Name: py3tftpsql
Version: 1.0.2
Summary: Python 3 asynchronous TFTP server.
Home-page: https://github.com/gt732/py3tftp-sql
Author: Matt O.
Author-email: matt@mattscodecave.com
License: MIT
Keywords: async asynchronous tftp
Classifier: Development Status :: 5 - Production/Stable
Classifier: Intended Audience :: Developers
Classifier: Intended Audience :: System Administrators
Classifier: Programming Language :: Python :: 3 :: Only
Classifier: Programming Language :: Python :: 3.5
Classifier: Programming Language :: Python :: 3.6
Classifier: Programming Language :: Python :: 3.7
Classifier: Programming Language :: Python :: 3.8
Classifier: Programming Language :: Python :: 3.9
Classifier: Topic :: Utilities
Classifier: Topic :: Software Development
Classifier: License :: OSI Approved :: MIT License
License-File: LICENSE
